{
  "project_info": {
    "project_number": "737651613348",
    "project_id": "catat-keuangan-c0a5f",
    "storage_bucket": "catat-keuangan-c0a5f.appspot.com"
  },
  "client": [
    {
      "client_info": {
        "mobilesdk_app_id": "1:737651613348:android:d9f9024ba7d89965cc5031",
        "android_client_info": {
          "package_name": "com.sasat.catat_keuangan"
        }
      },
      "oauth_client": [],
      "api_key": [
        {
          "current_key": "AIzaSyC_sx7_5quloKE9uoH-xDveYvlfvp3j4Hw"
        }
      ],
      "services": {
        "appinvite_service": {
          "other_platform_oauth_client": []
        }
      }
    }
  ],
  "configuration_version": "1"
}